bluegill/__init__.py
bluegill-0.0.1.dist-info/LICENSE
bluegill-0.0.1.dist-info/METADATA
bluegill-0.0.1.dist-info/WHEEL
bluegill-0.0.1.dist-info/top_level.txt
bluegill-0.0.1.dist-info/RECORD
